Workbook

Sheet PARAMETROS
A1: Parámetro | B1: Valor / captura | C1: Orientación
A2: Proyecto | B2: Monchis Café — Plataforma Web y POS Seguro para Cafetería Orgánica | C2: Cambiar por el proyecto elegido
A3: Año | B3: 2026 | C3: Tarifa ISR mensual para nóminas
A4: Duración (meses) | B4: 4 | C4: Meses de ejecución
A5: Proyectos a entregar | B5: 1 | C5: Cantidad de soluciones idénticas a comercializar
A6: Margen deseado sobre venta | B6: 0.3 | C6: Ejemplo 0.30 significa utilidad 30% del precio sin IVA
A7: IVA facturación | B7: 0.16 | C7: Se adiciona al precio; no es utilidad
A8: Contingencia sobre costo | B8: 0.1 | C8: Reserva para imprevistos
A9: Carga patronal estimada | B9: 0.3 | C9: SUPUESTO académico ajustable, no cálculo definitivo IMSS / INFONAVIT
A10: Horas productivas al mes | B10: 160 | C10: Para estimar costo por hora
A11: UMA diaria 2026 | B11: 117.31 | C11: INEGI vigente desde 01/02/2026
A12: Subsidio empleo ingreso máximo | B12: 11492.66 | C12: Límite mensual establecido para 2026
A13: Subsidio mensual 2026 | B13: =ROUND(3566.22*15.02%,2) | C13: Valor general desde febrero; enero tiene excepción normativa
A14: Interés anual préstamo | B14: 0.18 | C14: Supuesto ajustable
A15: Plazo préstamo (meses) | B15: 24 | C15: Supuesto ajustable
A16: Costo de capital de inversión asignado | B16: 1 | C16: Fracción inversión inicial imputada al proyecto (0 a 1)

Sheet ISR 2026 MENSUAL
A1: Límite inferior | B1: Límite superior | C1: Cuota fija | D1: Tasa excedente | E1: Fuente / aplicación
A2: 0.01 | B2: 844.59 | C2: 0 | D2: 0.0192 | E2: SAT / DOF Anexo 8 RMF 2026, retención mensual salarios
A3: 844.6 | B3: 7168.51 | C3: 16.22 | D3: 0.064 | E3: SAT / DOF Anexo 8 RMF 2026, retención mensual salarios
A4: 7168.52 | B4: 12598.02 | C4: 420.95 | D4: 0.1088 | E4: SAT / DOF Anexo 8 RMF 2026, retención mensual salarios
A5: 12598.03 | B5: 14644.64 | C5: 1011.68 | D5: 0.16 | E5: SAT / DOF Anexo 8 RMF 2026, retención mensual salarios
A6: 14644.65 | B6: 17533.64 | C6: 1339.14 | D6: 0.1792 | E6: SAT / DOF Anexo 8 RMF 2026, retención mensual salarios
A7: 17533.65 | B7: 35362.83 | C7: 1856.84 | D7: 0.2136 | E7: SAT / DOF Anexo 8 RMF 2026, retención mensual salarios
A8: 35362.84 | B8: 55736.68 | C8: 5665.16 | D8: 0.2352 | E8: SAT / DOF Anexo 8 RMF 2026, retención mensual salarios
A9: 55736.69 | B9: 106410.5 | C9: 10457.09 | D9: 0.3 | E9: SAT / DOF Anexo 8 RMF 2026, retención mensual salarios
A10: 106410.51 | B10: 141880.66 | C10: 25659.23 | D10: 0.32 | E10: SAT / DOF Anexo 8 RMF 2026, retención mensual salarios
A11: 141880.67 | B11: 425641.99 | C11: 37009.69 | D11: 0.34 | E11: SAT / DOF Anexo 8 RMF 2026, retención mensual salarios
A12: 425642 | B12: 999999999 | C12: 133488.54 | D12: 0.35 | E12: SAT / DOF Anexo 8 RMF 2026, retención mensual salarios
A15: Referencia oficial: https://sidof.segob.gob.mx/notas/docFuente/5777219
A16: No equivale a ISR empresarial sobre utilidades. ISR se retiene al trabajador.

Sheet NOMINA
A1: Puesto | B1: Sueldo mensual / persona | C1: Personas | D1: Sueldo bruto total | E1: ISR por persona | F1: ISR total | G1: Subsidio por persona | H1: Neto mensual total | I1: Carga patronal estimada | J1: Costo mensual empresa | K1: Horas mes equipo | L1: Costo por hora
A2: Scrum Master / líder | B2: 36000 | C2: 1 | D2: =B2*C2 | E2: =IF(B2<=0,0,ROUND(INDEX('ISR 2026 MENSUAL'!$C$2:$C$12,MATCH(B2,'ISR 2026 MENSUAL'!$A$2:$A$12,1))+(B2-INDEX('ISR 2026 MENSUAL'!$A$2:$A$12,MATCH(B2,'ISR 2026 MENSUAL'!$A$2:$A$12,1)))*INDEX('ISR 2026 MENSUAL'!$D$2:$D$12,MATCH(B2,'ISR 2026 MENSUAL'!$A$2:$A$12,1)),2)) | F2: =MAX(0,(E2-G2)*C2) | G2: =IF(AND(B2>0,B2<=PARAMETROS!$B$12),MIN(E2,PARAMETROS!$B$13),0) | H2: =D2-F2 | I2: =D2*PARAMETROS!$B$9 | J2: =D2+I2 | K2: =C2*PARAMETROS!$B$10 | L2: =IFERROR(J2/K2,0)
A3: Desarrollador frontend | B3: 20000 | C3: 1 | D3: =B3*C3 | E3: =IF(B3<=0,0,ROUND(INDEX('ISR 2026 MENSUAL'!$C$2:$C$12,MATCH(B3,'ISR 2026 MENSUAL'!$A$2:$A$12,1))+(B3-INDEX('ISR 2026 MENSUAL'!$A$2:$A$12,MATCH(B3,'ISR 2026 MENSUAL'!$A$2:$A$12,1)))*INDEX('ISR 2026 MENSUAL'!$D$2:$D$12,MATCH(B3,'ISR 2026 MENSUAL'!$A$2:$A$12,1)),2)) | F3: =MAX(0,(E3-G3)*C3) | G3: =IF(AND(B3>0,B3<=PARAMETROS!$B$12),MIN(E3,PARAMETROS!$B$13),0) | H3: =D3-F3 | I3: =D3*PARAMETROS!$B$9 | J3: =D3+I3 | K3: =C3*PARAMETROS!$B$10 | L3: =IFERROR(J3/K3,0)
A4: Desarrollador backend | B4: 20000 | C4: 1 | D4: =B4*C4 | E4: =IF(B4<=0,0,ROUND(INDEX('ISR 2026 MENSUAL'!$C$2:$C$12,MATCH(B4,'ISR 2026 MENSUAL'!$A$2:$A$12,1))+(B4-INDEX('ISR 2026 MENSUAL'!$A$2:$A$12,MATCH(B4,'ISR 2026 MENSUAL'!$A$2:$A$12,1)))*INDEX('ISR 2026 MENSUAL'!$D$2:$D$12,MATCH(B4,'ISR 2026 MENSUAL'!$A$2:$A$12,1)),2)) | F4: =MAX(0,(E4-G4)*C4) | G4: =IF(AND(B4>0,B4<=PARAMETROS!$B$12),MIN(E4,PARAMETROS!$B$13),0) | H4: =D4-F4 | I4: =D4*PARAMETROS!$B$9 | J4: =D4+I4 | K4: =C4*PARAMETROS!$B$10 | L4: =IFERROR(J4/K4,0)
A5: Product Owner / analista | D5: =B5*C5 | E5: =IF(B5<=0,0,ROUND(INDEX('ISR 2026 MENSUAL'!$C$2:$C$12,MATCH(B5,'ISR 2026 MENSUAL'!$A$2:$A$12,1))+(B5-INDEX('ISR 2026 MENSUAL'!$A$2:$A$12,MATCH(B5,'ISR 2026 MENSUAL'!$A$2:$A$12,1)))*INDEX('ISR 2026 MENSUAL'!$D$2:$D$12,MATCH(B5,'ISR 2026 MENSUAL'!$A$2:$A$12,1)),2)) | F5: =MAX(0,(E5-G5)*C5) | G5: =IF(AND(B5>0,B5<=PARAMETROS!$B$12),MIN(E5,PARAMETROS!$B$13),0) | H5: =D5-F5 | I5: =D5*PARAMETROS!$B$9 | J5: =D5+I5 | K5: =C5*PARAMETROS!$B$10 | L5: =IFERROR(J5/K5,0)
A6: Diseñador UX/UI | D6: =B6*C6 | E6: =IF(B6<=0,0,ROUND(INDEX('ISR 2026 MENSUAL'!$C$2:$C$12,MATCH(B6,'ISR 2026 MENSUAL'!$A$2:$A$12,1))+(B6-INDEX('ISR 2026 MENSUAL'!$A$2:$A$12,MATCH(B6,'ISR 2026 MENSUAL'!$A$2:$A$12,1)))*INDEX('ISR 2026 MENSUAL'!$D$2:$D$12,MATCH(B6,'ISR 2026 MENSUAL'!$A$2:$A$12,1)),2)) | F6: =MAX(0,(E6-G6)*C6) | G6: =IF(AND(B6>0,B6<=PARAMETROS!$B$12),MIN(E6,PARAMETROS!$B$13),0) | H6: =D6-F6 | I6: =D6*PARAMETROS!$B$9 | J6: =D6+I6 | K6: =C6*PARAMETROS!$B$10 | L6: =IFERROR(J6/K6,0)
A7: QA / pruebas | B7: 13500 | C7: 1 | D7: =B7*C7 | E7: =IF(B7<=0,0,ROUND(INDEX('ISR 2026 MENSUAL'!$C$2:$C$12,MATCH(B7,'ISR 2026 MENSUAL'!$A$2:$A$12,1))+(B7-INDEX('ISR 2026 MENSUAL'!$A$2:$A$12,MATCH(B7,'ISR 2026 MENSUAL'!$A$2:$A$12,1)))*INDEX('ISR 2026 MENSUAL'!$D$2:$D$12,MATCH(B7,'ISR 2026 MENSUAL'!$A$2:$A$12,1)),2)) | F7: =MAX(0,(E7-G7)*C7) | G7: =IF(AND(B7>0,B7<=PARAMETROS!$B$12),MIN(E7,PARAMETROS!$B$13),0) | H7: =D7-F7 | I7: =D7*PARAMETROS!$B$9 | J7: =D7+I7 | K7: =C7*PARAMETROS!$B$10 | L7: =IFERROR(J7/K7,0)
A8: Administrador BD | D8: =B8*C8 | E8: =IF(B8<=0,0,ROUND(INDEX('ISR 2026 MENSUAL'!$C$2:$C$12,MATCH(B8,'ISR 2026 MENSUAL'!$A$2:$A$12,1))+(B8-INDEX('ISR 2026 MENSUAL'!$A$2:$A$12,MATCH(B8,'ISR 2026 MENSUAL'!$A$2:$A$12,1)))*INDEX('ISR 2026 MENSUAL'!$D$2:$D$12,MATCH(B8,'ISR 2026 MENSUAL'!$A$2:$A$12,1)),2)) | F8: =MAX(0,(E8-G8)*C8) | G8: =IF(AND(B8>0,B8<=PARAMETROS!$B$12),MIN(E8,PARAMETROS!$B$13),0) | H8: =D8-F8 | I8: =D8*PARAMETROS!$B$9 | J8: =D8+I8 | K8: =C8*PARAMETROS!$B$10 | L8: =IFERROR(J8/K8,0)
A9: DevOps / nube | D9: =B9*C9 | E9: =IF(B9<=0,0,ROUND(INDEX('ISR 2026 MENSUAL'!$C$2:$C$12,MATCH(B9,'ISR 2026 MENSUAL'!$A$2:$A$12,1))+(B9-INDEX('ISR 2026 MENSUAL'!$A$2:$A$12,MATCH(B9,'ISR 2026 MENSUAL'!$A$2:$A$12,1)))*INDEX('ISR 2026 MENSUAL'!$D$2:$D$12,MATCH(B9,'ISR 2026 MENSUAL'!$A$2:$A$12,1)),2)) | F9: =MAX(0,(E9-G9)*C9) | G9: =IF(AND(B9>0,B9<=PARAMETROS!$B$12),MIN(E9,PARAMETROS!$B$13),0) | H9: =D9-F9 | I9: =D9*PARAMETROS!$B$9 | J9: =D9+I9 | K9: =C9*PARAMETROS!$B$10 | L9: =IFERROR(J9/K9,0)
A10: Soporte / documentación | D10: =B10*C10 | E10: =IF(B10<=0,0,ROUND(INDEX('ISR 2026 MENSUAL'!$C$2:$C$12,MATCH(B10,'ISR 2026 MENSUAL'!$A$2:$A$12,1))+(B10-INDEX('ISR 2026 MENSUAL'!$A$2:$A$12,MATCH(B10,'ISR 2026 MENSUAL'!$A$2:$A$12,1)))*INDEX('ISR 2026 MENSUAL'!$D$2:$D$12,MATCH(B10,'ISR 2026 MENSUAL'!$A$2:$A$12,1)),2)) | F10: =MAX(0,(E10-G10)*C10) | G10: =IF(AND(B10>0,B10<=PARAMETROS!$B$12),MIN(E10,PARAMETROS!$B$13),0) | H10: =D10-F10 | I10: =D10*PARAMETROS!$B$9 | J10: =D10+I10 | K10: =C10*PARAMETROS!$B$10 | L10: =IFERROR(J10/K10,0)
A11: Otro 1 | D11: =B11*C11 | E11: =IF(B11<=0,0,ROUND(INDEX('ISR 2026 MENSUAL'!$C$2:$C$12,MATCH(B11,'ISR 2026 MENSUAL'!$A$2:$A$12,1))+(B11-INDEX('ISR 2026 MENSUAL'!$A$2:$A$12,MATCH(B11,'ISR 2026 MENSUAL'!$A$2:$A$12,1)))*INDEX('ISR 2026 MENSUAL'!$D$2:$D$12,MATCH(B11,'ISR 2026 MENSUAL'!$A$2:$A$12,1)),2)) | F11: =MAX(0,(E11-G11)*C11) | G11: =IF(AND(B11>0,B11<=PARAMETROS!$B$12),MIN(E11,PARAMETROS!$B$13),0) | H11: =D11-F11 | I11: =D11*PARAMETROS!$B$9 | J11: =D11+I11 | K11: =C11*PARAMETROS!$B$10 | L11: =IFERROR(J11/K11,0)
A12: Otro 2 | D12: =B12*C12 | E12: =IF(B12<=0,0,ROUND(INDEX('ISR 2026 MENSUAL'!$C$2:$C$12,MATCH(B12,'ISR 2026 MENSUAL'!$A$2:$A$12,1))+(B12-INDEX('ISR 2026 MENSUAL'!$A$2:$A$12,MATCH(B12,'ISR 2026 MENSUAL'!$A$2:$A$12,1)))*INDEX('ISR 2026 MENSUAL'!$D$2:$D$12,MATCH(B12,'ISR 2026 MENSUAL'!$A$2:$A$12,1)),2)) | F12: =MAX(0,(E12-G12)*C12) | G12: =IF(AND(B12>0,B12<=PARAMETROS!$B$12),MIN(E12,PARAMETROS!$B$13),0) | H12: =D12-F12 | I12: =D12*PARAMETROS!$B$9 | J12: =D12+I12 | K12: =C12*PARAMETROS!$B$10 | L12: =IFERROR(J12/K12,0)
A13: Otro 3 | D13: =B13*C13 | E13: =IF(B13<=0,0,ROUND(INDEX('ISR 2026 MENSUAL'!$C$2:$C$12,MATCH(B13,'ISR 2026 MENSUAL'!$A$2:$A$12,1))+(B13-INDEX('ISR 2026 MENSUAL'!$A$2:$A$12,MATCH(B13,'ISR 2026 MENSUAL'!$A$2:$A$12,1)))*INDEX('ISR 2026 MENSUAL'!$D$2:$D$12,MATCH(B13,'ISR 2026 MENSUAL'!$A$2:$A$12,1)),2)) | F13: =MAX(0,(E13-G13)*C13) | G13: =IF(AND(B13>0,B13<=PARAMETROS!$B$12),MIN(E13,PARAMETROS!$B$13),0) | H13: =D13-F13 | I13: =D13*PARAMETROS!$B$9 | J13: =D13+I13 | K13: =C13*PARAMETROS!$B$10 | L13: =IFERROR(J13/K13,0)
A15: TOTAL MENSUAL | D15: =SUM(D2:D13) | F15: =SUM(F2:F13) | H15: =SUM(H2:H13) | I15: =SUM(I2:I13) | J15: =SUM(J2:J13) | K15: =SUM(K2:K13)
A17: ISR = retención al trabajador, no costo patronal adicional.
A18: Carga patronal: estimación académica configurable; no sustituye cálculo IMSS con SBC, prima riesgo y cuotas reales.

Sheet GASTOS FIJOS
A1: Concepto | B1: Mensual MXN | C1: Meses imputados | D1: Total del proyecto | E1: Criterio
A2: Renta / espacio | B2: 6000 | C2: =PARAMETROS!$B$4 | D2: =B2*C2 | E2: Espacio de trabajo colaborativo/coworking y sala de juntas para reuniones de sprint y trabajo presencial
A3: Electricidad | B3: 1200 | C3: =PARAMETROS!$B$4 | D3: =B3*C3 | E3: Consumo eléctrico de estaciones de cómputo, servidores de desarrollo local y climatización
A4: Internet / telefonía | B4: 1500 | C4: =PARAMETROS!$B$4 | D4: =B4*C4 | E4: Enlace empresarial simétrico de fibra óptica 500 Mbps con IP fija para pruebas y telefonía IP
A5: Administración y contabilidad | B5: 2500 | C5: =PARAMETROS!$B$4 | D5: =B5*C5 | E5: Servicios de despacho contable externo, dispersión de nóminas, timbrado de CFDI y declaraciones SAT
A6: Herramientas compartidas | B6: 1800 | C6: =PARAMETROS!$B$4 | D6: =B6*C6 | E6: Suscripciones compartidas de equipo: Google Workspace, Slack Pro, Notion Team y Figma Professional
A7: Publicidad / ventas | B7: 1000 | C7: =PARAMETROS!$B$4 | D7: =B7*C7 | E7: Gastos comerciales de gestión de cuenta, demostraciones en sitio con el cliente y material de presentación
A8: Otros gastos fijos | B8: 1000 | C8: =PARAMETROS!$B$4 | D8: =B8*C8 | E8: Mantenimiento preventivo, artículos de limpieza, papelería técnica y suministros de oficina
A9: TOTAL GASTOS FIJOS | D9: =SUM(D2:D8)

Sheet COSTOS DIRECTOS
A1: Concepto | B1: Unidad | C1: Cantidad por proyecto | D1: Costo unitario | E1: Costo total | F1: Notas
A2: Servicios de nube / hosting | B2: Meses | C2: 4 | D2: 1800 | E2: =C2*D2 | F2: Google Cloud Platform: Cloud Run (microservicios), Cloud SQL PostgreSQL, Redis Memorystore
A3: Licencias del proyecto | B3: Meses | C3: 4 | D3: 600 | E3: =C3*D3 | F3: GitHub Team (repositorios privados, minutos CI/CD Actions) y monitoreo de excepciones con Sentry
A4: APIs de terceros | B4: Meses | C4: 4 | D4: 550 | E4: =C4*D4 | F4: CloudAMQP (RabbitMQ dedicado gestionado para eventos asíncronos, Patrón Saga y Dead Letter Queue)
A5: Dominio / SSL | B5: Licencia anual | C5: 1 | D5: 950 | E5: =C5*D5 | F5: Registro de dominio oficial corporativo .com.mx y certificado de seguridad TLS/SSL Wildcard 256 bits
A6: Pruebas / dispositivos | B6: Dispositivos/Lic | C6: 2 | D6: 1500 | E6: =C6*D6 | F6: Dispositivos móviles de laboratorio para testing multi-resolución, soporte táctil y escaneo de códigos QR
A7: Subcontratación | B7: Servicio | C7: 1 | D7: 4500 | E7: =C7*D7 | F7: Auditoría de ciberseguridad externa y pentesting ético sobre autenticación JWT y pasarela de pago
A8: Viáticos | B8: Visitas en sitio | C8: 6 | D8: 500 | E8: =C8*D8 | F8: Traslados a cafetería en La Piedad para levantamiento, instalación física de terminales y pruebas en barra
A9: Material y consumibles | B9: Lote | C9: 1 | D9: 850 | E9: =C9*D9 | F9: Rollos de papel térmico 80mm libre de BPA para pruebas de tickets de barra, cables USB/red blindados
A10: Seguridad / auditoría | B10: Servicio | C10: 1 | D10: 1200 | E10: =C10*D10 | F10: Escaneos automatizados de código estático (SAST) y dependencias con reportes OWASP Top 10
A11: Otros costos directos | B11: Paquete | C11: 1 | D11: 1500 | E11: =C11*D11 | F11: Manuales operativos impresos de mostrador, señalética de sellos Monchis Rewards y packaging demo
A12: TOTAL COSTOS DIRECTOS | E12: =SUM(E2:E11)

Sheet INVERSION INICIAL
A1: Activo / gasto inicial | B1: Cantidad | C1: Precio unitario | D1: Importe | E1: Vida útil (meses) | F1: Meses asignados al proyecto | G1: Costo imputado proyecto
A2: Equipo de cómputo | B2: 4 | C2: 22000 | D2: =B2*C2 | E2: 36 | F2: =PARAMETROS!$B$4 | G2: =IFERROR(D2*MIN(1,F2/E2)*PARAMETROS!$B$16,0)
A3: Mobiliario | B3: 4 | C3: 4500 | D3: =B3*C3 | E3: 60 | F3: =PARAMETROS!$B$4 | G3: =IFERROR(D3*MIN(1,F3/E3)*PARAMETROS!$B$16,0)
A4: Equipo de red | B4: 1 | C4: 8500 | D4: =B4*C4 | E4: 36 | F4: =PARAMETROS!$B$4 | G4: =IFERROR(D4*MIN(1,F4/E4)*PARAMETROS!$B$16,0)
A5: Licencias de instalación | B5: 4 | C5: 3200 | D5: =B5*C5 | E5: 24 | F5: =PARAMETROS!$B$4 | G5: =IFERROR(D5*MIN(1,F5/E5)*PARAMETROS!$B$16,0)
A6: Capacitación / puesta en marcha | B6: 1 | C6: 12000 | D6: =B6*C6 | E6: 12 | F6: =PARAMETROS!$B$4 | G6: =IFERROR(D6*MIN(1,F6/E6)*PARAMETROS!$B$16,0)
A7: Otro activo | B7: 1 | C7: 9500 | D7: =B7*C7 | E7: 24 | F7: =PARAMETROS!$B$4 | G7: =IFERROR(D7*MIN(1,F7/E7)*PARAMETROS!$B$16,0)
A8: TOTALES | D8: =SUM(D2:D7) | G8: =SUM(G2:G7)

Sheet PRESTAMO
A1: Concepto | B1: Importe / factor | C1: Explicación
A2: Monto financiado | B2: 40000 | C2: Capturar solo si el proyecto tendrá financiación
A3: Tasa anual | B3: =PARAMETROS!B14 | C3: Tasa editable en parámetros
A4: Meses crédito | B4: =PARAMETROS!B15 | C4: Plazo editable en parámetros
A5: Cuota mensual | B5: =IFERROR(IF(B3=0,B2/B4,PMT(B3/12,B4,-B2)),0) | C5: Pago mensual a interés compuesto
A6: Interés aproximado del proyecto | B6: =IFERROR(MAX(0,(B5*MIN(PARAMETROS!B4,B4))-(B2/B4*MIN(PARAMETROS!B4,B4))),0)

Sheet RESUMEN Y COTIZACION
A1: Presupuesto del proyecto | B1: Resultado MXN | C1: Interpretación
A2: Proyecto | B2: =PARAMETROS!B2
A3: Duración meses | B3: =PARAMETROS!B4
A4: Unidades / proyectos | B4: =PARAMETROS!B5
A6: Nómina y carga patronal | B6: =NOMINA!J15*PARAMETROS!B4
A7: Gastos fijos | B7: ='GASTOS FIJOS'!D9
A8: Costos directos | B8: ='COSTOS DIRECTOS'!E12*PARAMETROS!B5
A9: Inversión inicial asignada | B9: ='INVERSION INICIAL'!G8
A10: Intereses de financiamiento | B10: =PRESTAMO!B6
A11: COSTO BASE TOTAL | B11: =SUM(B6:B10) | C11: Incluye costos empresariales, NO ISR retenido de trabajadores como costo adicional.
A12: Contingencia | B12: =B11*PARAMETROS!B8
A13: COSTO TOTAL DEL PROYECTO | B13: =SUM(B11:B12)
A14: Costo unitario por proyecto | B14: =IFERROR(B13/B4,0)
A16: Margen sobre precio | B16: =PARAMETROS!B6
A17: PRECIO DE VENTA SIN IVA / UNIDAD | B17: =IFERROR(B14/(1-B16),0) | C17: Precio = costo unitario / (1 - margen). No confundir margen con recargo.
A18: IVA por unidad | B18: =B17*PARAMETROS!B7
A19: PRECIO DE VENTA CON IVA / UNIDAD | B19: =SUM(B17:B18)
A20: COTIZACIÓN TOTAL SIN IVA | B20: =B17*B4
A21: IVA TOTAL | B21: =B18*B4
A22: COTIZACIÓN TOTAL CON IVA | B22: =B19*B4
A24: Utilidad proyectada (antes ISR empresarial) | B24: =B20-B13
A25: Rentabilidad sobre ventas | B25: =IFERROR(B24/B20,0)
A26: Punto de equilibrio (unidades) | B26: =IFERROR(ROUNDUP((B6+B7+B9+B10)/(B17-(B8/B4)-(B12/B4)),0),0) | C26: Estimación simplificada para proyectos repetibles; no usar como PE contable definitivo.

Sheet INSTRUCCIONES
A1: Paso | B1: Acción / criterio
A2: 1 | B2: Captura datos únicamente en celdas amarillas de PARAMETROS, NOMINA, GASTOS FIJOS, COSTOS DIRECTOS, INVERSION INICIAL y PRESTAMO.
A3: 2 | B3: En NOMINA escribe sueldo mensual BRUTO por persona y número de personas. La retención de ISR se consulta automáticamente en tabla 2026.
A4: 3 | B4: Duración y número de proyectos controlan los importes acumulados. Evita duplicar equipos de cómputo como gasto directo y como inversión.
A5: 4 | B5: En INVERSION INICIAL captura vida útil en meses: el sistema distribuye el gasto según duración del proyecto.
A6: 5 | B6: El precio se calcula aplicando margen comercial antes de IVA. ISR retenido a empleados NO es ISR de la empresa.
A7: 6 | B7: El costo patronal se aproxima con una tasa editable; verificar caso real (SBC, IMSS, INFONAVIT, impuesto nómina, prestaciones).
A8: 7 | B8: El subsidio al empleo corresponde a la regla general desde febrero de 2026; enero requiere tratamiento específico.
A9: 8 | B9: Resultados y cotización final en RESUMEN Y COTIZACION. Todos los importes en pesos mexicanos.
A10: FUENTE ISR | B10: https://sidof.segob.gob.mx/notas/docFuente/5777219
A11: FUENTE UMA | B11: https://www.inegi.org.mx/temas/uma/
A12: SUBSIDIO | B12: https://sidof.segob.gob.mx/notas/docFuente/5777649

Sheet ESTRATEGIA DE VENTA
B2: MONCHIS CAFÉ — ESTRATEGIA COMERCIAL DE VENTA Y JUSTIFICACIÓN FINANCIERA
B3: Actividad 4: Gestión de Finanzas | Proyecto Integrador de Software Seguro y Trazable (ODS)
B5: Proyecto Integrador: | C5: Monchis Café — Plataforma Web y POS Seguro para Cafetería Orgánica | E5: Docente: | F5: Dr. Gabriel Navarro Salcedo
B6: Estudiante: | C6: Ernesto Hatuey Fierro Meléndez | E6: Asignatura: | F6: Gestión de Finanzas / Admón. de Proyectos
B7: Empresa Desarrolladora: | C7: Soluciones Digitales Fierro & Asociados S.A.S. de C.V. | E7: Fecha de Entrega: | F7: 24 de Octubre de 2026
B9: 1. RESUMEN EJECUTIVO DE COSTOS, PRECIO Y UTILIDAD DEL PROYECTO
B10: Indicador Financiero Clave | C10: Valor (MXN) | D10: Referencia Celda | E10: % s/ Venta | F10: Interpretación Financiera | G10: Relevancia Estratégica para el Negocio
B11: Costo Base Total (CTB) | C11: ='RESUMEN Y COTIZACION'!B11 | D11: ='RESUMEN Y COTIZACION'!A11 | E11: =C11/'RESUMEN Y COTIZACION'!$B$20 | F11: Costos empresariales directos e indirectos. | G11: Suma de nómina calificada, gastos fijos, nube, depreciación y costo financiero.
B12: Fondo de Contingencia (10%) | C12: ='RESUMEN Y COTIZACION'!B12 | D12: ='RESUMEN Y COTIZACION'!A12 | E12: =C12/'RESUMEN Y COTIZACION'!$B$20 | F12: Reserva de mitigación ante riesgos. | G12: Amortigua variaciones en tarifas cloud en USD, picos de tráfico y retrabajos menores.
B13: COSTO TOTAL DEL PROYECTO (CTP) | C13: ='RESUMEN Y COTIZACION'!B13 | D13: ='RESUMEN Y COTIZACION'!A13 | E13: =C13/'RESUMEN Y COTIZACION'!$B$20 | F13: Inversión neta para producir la solución. | G13: Inversión indispensable para cubrir los 8 sprints de desarrollo y aseguramiento de calidad.
B14: Margen de Utilidad sobre Ventas | C14: ='RESUMEN Y COTIZACION'!B16 | D14: ='RESUMEN Y COTIZACION'!A16 | E14: =C14 | F14: Rendimiento comercial del 30.0%. | G14: Margen real sobre precio facturado sin IVA, garantizando viabilidad económica corporativa.
B15: PRECIO DE VENTA SIN IVA (COTIZACIÓN) | C15: ='RESUMEN Y COTIZACION'!B17 | D15: ='RESUMEN Y COTIZACION'!A17 | E15: =C15/'RESUMEN Y COTIZACION'!$B$20 | F15: Precio comercial fijado: CTP / (1 - Margen). | G15: Cotización base de la solución completa llave en mano con entrega en la nube.
B16: IVA Trasladado (16%) | C16: ='RESUMEN Y COTIZACION'!B18 | D16: ='RESUMEN Y COTIZACION'!A18 | E16: =C16/'RESUMEN Y COTIZACION'!$B$20 | F16: Impuesto fiscal trasladado por ley. | G16: Obligación tributaria ante el SAT; deducible para el cliente como inversión de capital.
B17: PRECIO TOTAL FACTURADO CON IVA | C17: ='RESUMEN Y COTIZACION'!B19 | D17: ='RESUMEN Y COTIZACION'!A19 | E17: =C17/'RESUMEN Y COTIZACION'!$B$20 | F17: Monto contractual total formalizado. | G17: Importe global formal suscrito en el contrato de prestación de servicios informáticos.
B18: UTILIDAD BRUTA PROYECTADA | C18: ='RESUMEN Y COTIZACION'!B24 | D18: ='RESUMEN Y COTIZACION'!A24 | E18: =C18/'RESUMEN Y COTIZACION'!$B$20 | F18: Ganancia bruta de la empresa desarrolladora. | G18: Retorno del 30% neto previo a impuestos corporativos anuales para reinversión e I+D.
B19: Punto de Equilibrio (Soluciones) | C19: ='RESUMEN Y COTIZACION'!B26 | D19: ='RESUMEN Y COTIZACION'!A26 | E19: N/A | F19: 1 proyecto único llave en mano. | G19: La comercialización del sistema al cliente Monchis Café cubre el 100% de la estructura de costos.
B21: 2. CUADRO JUSTIFICATIVO DE PERTINENCIA DE COSTOS DEL PROYECTO
B22: Rubro de Costo Presupuestal | C22: Importe (MXN) | D22: % s/ CTP | E22: Tipo de Costo | F22: Criterio Técnico y Pertinencia Operativa | G22: Impacto en la Calidad y Viabilidad Técnica
B23: Nómina y Carga Patronal (4 meses) | C23: ='RESUMEN Y COTIZACION'!B6 | D23: =C23/'RESUMEN Y COTIZACION'!$B$13 | E23: Mano de Obra Directa | F23: 4 perfiles técnicos: Líder/Scrum Master & DevOps ($36k), Frontend Vue 3 ($20k), Backend Next.js ($20k) y QA Ciberseguridad ($13.5k) por 16 semanas (2,560 hrs). Incluye 30% de carga patronal estimada (IMSS, Infonavit, ISN 3%). | G23: Garantiza el cumplimiento estricto del cronograma de 8 sprints, desarrollo TDD con cobertura >80% y arquitectura resiliente sin rotación de talento.
B24: Gastos Fijos Operativos Imputados | C24: ='RESUMEN Y COTIZACION'!B7 | D24: =C24/'RESUMEN Y COTIZACION'!$B$13 | E24: Costo Indirecto Fijo | F24: Oficina coworking ($6k/mes), energía eléctrica ($1.2k), fibra simétrica 500 Mbps con IP fija ($1.5k), despacho contable/fiscal ($2.5k), herramientas compartidas ($1.8k) y suministros ($2k) imputados al 100% en los 4 meses ($60k total). | G24: Brinda infraestructura física y legal idónea para operar sin disrupciones de conectividad, auditorías fiscales al día y herramientas de colaboración ágil.
B25: Costos Directos de Nube y Servicios | C25: ='RESUMEN Y COTIZACION'!B8 | D25: =C25/'RESUMEN Y COTIZACION'!$B$13 | E25: Costo Directo Variable | F25: Infraestructura GCP (Cloud Run, Cloud SQL PostgreSQL, Redis: $7.2k), broker RabbitMQ en CloudAMQP ($2.2k), dominio/SSL ($950), pentesting externo ($4.5k), viáticos a barra ($3k) y material de prueba ($2.35k). | G25: Sustenta la arquitectura orientada a eventos, tolerancia a fallos con Dead Letter Queue (DLQ), seguridad bancaria y validación in situ del hardware de mostrador.
B26: Inversión Inicial Asignada (Depreciación) | C26: ='RESUMEN Y COTIZACION'!B9 | D26: =C26/'RESUMEN Y COTIZACION'!$B$13 | E26: Depreciación de Activos | F26: Depreciación proporcional en 4 meses de 4 laptops de desarrollo (36 meses vida útil), mobiliario ergonómico (60 meses), red gigabit (36 meses), licencias IDEs (24 meses), capacitación RabbitMQ (12 meses) y kit POS laboratorio (24 meses). | G26: Aplica el principio contable de devengo: el proyecto absorbe únicamente la fracción de desgaste de los activos productivos durante su ejecución ($19,638.89 de $148.8k adquiridos).
B27: Intereses por Financiamiento Puente | C27: ='RESUMEN Y COTIZACION'!B10 | D27: =C27/'RESUMEN Y COTIZACION'!$B$13 | E27: Costo Financiero | F27: Línea de crédito para capital de trabajo de $40,000.00 MXN al 18% anual a 24 meses para financiar el arranque y compra de activos antes del primer cobro de hitos. Interés imputado en 4 meses: $1,321.19 MXN. | G27: Otorga liquidez inmediata en el Día 1, protegiendo el flujo de efectivo operativo frente a demoras en la validación de entregables del cliente.
B28: Fondo de Contingencia y Riesgos (10%) | C28: ='RESUMEN Y COTIZACION'!B12 | D28: =C28/'RESUMEN Y COTIZACION'!$B$13 | E28: Gestión de Riesgos | F28: Reserva estratégica del 10% calculada sobre el costo base total ($57,316.01 MXN), destinada a mitigar desvíos en consumo de cómputo en la nube, fluctuaciones en tipo de cambio USD/MXN y retrabajos menores. | G28: Blindaje financiero para absorber imprevistos sin comprometer la rentabilidad pactada ni incurrir en sobrecostos no autorizados.
B29: TOTAL COSTO INTEGRAL DEL PROYECTO | C29: ='RESUMEN Y COTIZACION'!B13 | D29: =C29/'RESUMEN Y COTIZACION'!$B$13 | E29: Costo Total Absoluto | F29: Suma integral de todos los factores de costo empresarial necesarios para desarrollar, probar y liberar en producción la plataforma web y POS Monchis Café. | G29: Base analítica sólida para la determinación del precio comercial y justificación técnica ante el comité directivo del cliente.
B31: 3. ESTRATEGIA DE VENTA COMERCIAL SEGÚN COSTO Y UTILIDAD
B32: A. MODELO DE FIJACIÓN DE PRECIOS POR VALOR Y MARGEN REAL (PRICING STRATEGY)
B33: • Determinación del Precio Comercial: Se utiliza la metodología de margen sobre ventas antes de impuestos: Precio de Venta = Costo Total / (1 - Margen) = $630,476.09 / (1 - 0.30) = $900,680.12 MXN sin IVA ($1,044,788.94 MXN con IVA). • Margen vs Recargo (Markup): No se aplica un recargo simple sobre costos (que daría menor rendimiento), sino un margen real del 30.0% sobre el precio de venta facturado. Esto asegura una utilidad bruta de $270,204.04 MXN para la empresa desarrolladora. • Posicionamiento en el Mercado: La plataforma se posiciona como una solución de ingeniería de grado empresarial, desacoplada y trazable, superando a los POS comerciales genéricos que carecen de trazabilidad ODS, reversas automáticas y atribución digital de marketing.
B35: B. MODELO DE MONETIZACIÓN HÍBRIDO (IMPLEMENTACIÓN + INGRESOS RECURRENTES)
B36: 1. Venta Inicial Llave en Mano ($900,680.12 MXN + IVA): Licenciamiento perpetuo de la obra de software sobre infraestructura propia del cliente en Google Cloud Platform, configuración de microservicios, migración de catálogos y capacitación presencial a baristas y cajeros. 2. Póliza de Soporte, Mantenimiento Evolutivo y SLA ($18,500.00 MXN + IVA/mes a partir del Mes 5): - Disponibilidad 99.5% con monitoreo proactivo de microservicios y Dead Letter Queue (DLQ). - Ventana de respuesta crítica < 2 horas ante incidencias de cobro o bloqueo de caja. - Actualizaciones menores de dependencias, parches de seguridad y optimizaciones SEO continuas. - Margen operativo de la póliza: 55%, aportando un ingreso recurrente anual (ARR) de $222,000.00 MXN. 3. Módulo Adicional Opcional de Franquicias / Nuevas Sucursales: Licencia por sucursal adicional de $45,000.00 MXN + $3,500.00 MXN de soporte mensual si Monchis Café expande operaciones a nuevas ubicaciones.
B38: C. PROPUESTA DE VALOR Y RETORNO DE INVERSIÓN (ROI) PARA MONCHIS CAFÉ
B39: La inversión se justifica con beneficios operativos tangibles y medibles para la cafetería en su primer año de operación: • Reducción de Mermas de Café Orgánico (-22%): Ahorro mensual proyectado de $14,500.00 MXN mediante control PEPS y lotes regionales. • Incremento en Ticket Promedio (+24%): Generación de $38,500.00 MXN mensuales adicionales gracias a Monchis Rewards (sellos digitales y bonificación de termo -$5.00 MXN alineada a ODS 12). • Eliminación de Pérdidas por Fuga en Caja (-98%): Recuperación de $9,200.00 MXN mensuales por conciliación automática de pagos mixtos y control de cambio en efectivo. • Clientes Nuevos por SEO y Campañas Locales: Aportación de $16,800.00 MXN mensuales por tráfico de Google Maps e Instagram. • Beneficio Mensual Total para el Cliente: $79,000.00 MXN/mes → Beneficio Anual: $948,000.00 MXN. • Período de Recuperación (Payback Period): $900,680.12 / $79,000.00 = 11.4 meses. ¡La solución se paga sola en menos de un año!
B41: D. ESQUEMA DE CIERRE Y FINANCIAMIENTO POR HITOS ÁGILES (CASH FLOW PROTEGIDO)
B42: Para eliminar la fricción de compra y asegurar flujo de efectivo para el equipo, el cobro se divide en 5 exhibiciones contra entregables tangibles en Staging: • Hito 0 (Firma y Arranque): Anticipo del 20% ($180,136.02 MXN sin IVA) → Cubre licencias, activos y liquidez inicial. • Hito 1 (Sprint 2 - Backend & Seguridad): 15% ($135,102.02 MXN) → Backend Core, JWT stateless, RBAC y reCAPTCHA. • Hito 2 (Sprint 4 - Eventos & Frontend): 15% ($135,102.02 MXN) → RabbitMQ Topic Exchange, Patrón Saga y Frontend Vue 3. • Hito 3 (Sprint 6 - POS & Trazabilidad): 15% ($135,102.02 MXN) → POS mostrador, pagos mixtos y catálogo de café ODS 12. • Hito 4 (Sprint 8 - Dashboard & Testing): 15% ($135,102.02 MXN) → Dashboard analítico, atribución UTM y suites Vitest/Playwright. • Hito 5 (Cierre y Despliegue en GCP): Finiquito del 20% ($180,136.02 MXN) → Terraform en GCP, capacitación y entrega de llaves.
B44: 4. ANÁLISIS DE SENSIBILIDAD Y ESCENARIOS DE RENTABILIDAD
B45: Escenario Comercial | C45: Margen s/ Venta | D45: Precio sin IVA (MXN) | E45: Precio con IVA (16%) | F45: Utilidad Bruta Proyectada | G45: Criterio y Estrategia de Negociación
B46: Escenario Conservador (Piso Mínimo) | C46: 0.2 | D46: ='RESUMEN Y COTIZACION'!B13/(1-C46) | E46: =D46*1.16 | F46: =D46-'RESUMEN Y COTIZACION'!$B$13 | G46: Límite de descuento si el cliente exige reducción presupuestal; se ajusta recortando viáticos presenciales o auditorías externas.
B47: Escenario Esperado / Base (Recomendado) | C47: ='RESUMEN Y COTIZACION'!B16 | D47: ='RESUMEN Y COTIZACION'!B17 | E47: ='RESUMEN Y COTIZACION'!B19 | F47: ='RESUMEN Y COTIZACION'!B24 | G47: Propuesta base formal con 30.0% de margen. Maximiza valor, calidad arquitectónica y estabilidad de flujo de caja para la empresa.
B48: Escenario Premium / Valor Agregado | C48: 0.35 | D48: ='RESUMEN Y COTIZACION'!B13/(1-C48) | E48: =D48*1.16 | F48: =D48-'RESUMEN Y COTIZACION'!$B$13 | G48: Se ofrece integrando 6 meses de póliza de soporte 24/7 post-lanzamiento y analítica avanzada de fidelización y mermas.
B51: Documento generado para entrega académica de la Actividad 4: Gestión de Finanzas | Universidad de Guadalajara — Sistema de Educación Virtual / Presencial | Prohibida su reproducción total o parcial sin autorización.
